pagemeta/__init__.py
pagemeta/headers.py
pagemeta/main.py
pagemeta/meta.py
pagemeta-0.0.2.dist-info/METADATA
pagemeta-0.0.2.dist-info/WHEEL
pagemeta-0.0.2.dist-info/RECORD
